target/__init__.py
target/_logger.py
target/file.py
target/logging.conf
target/stream.py
target/api/__init__.py
target/api/client.py
target/api/test.py
target_core-0.1.0.dist-info/LICENSE
target_core-0.1.0.dist-info/METADATA
target_core-0.1.0.dist-info/WHEEL
target_core-0.1.0.dist-info/entry_points.txt
target_core-0.1.0.dist-info/top_level.txt
target_core-0.1.0.dist-info/RECORD
