Metadata-Version: 2.1
Name: target-core
Version: 0.1.0
Summary: Singer.io Target Core features
Home-page: https://gitlab.com/singer-core/target-core
Author: =?utf-8?b?RWRkeSDiiIY=?=
Author-email: edrdelta@gmail.com
License: Apache License 2.0
Project-URL: Documentation, https://singer-core.gitlab.io/target-core
Project-URL: Releases, https://gitlab.com/singer-core/target-core/-/releases
Project-URL: Changelog, https://gitlab.com/singer-core/target-core/blob/main/CHANGELOG.md
Project-URL: Issue Tracker, https://gitlab.com/singer-core/target-core/issues
Project-URL: Bug Tracker, https://gitlab.com/singer-core/target-core/issues/service_desk
Keywords: etl,singer,singer-core,tap,tap-core,target,target-core,target-s3-jsonl,target-s3-json
Classifier: Development Status :: 2 - Pre-Alpha
Classifier: Operating System :: OS Independent
Classifier: License :: OSI Approved :: Apache Software License
Classifier: Programming Language :: Python :: 3 :: Only
Classifier: Programming Language :: Python :: 3.9
Classifier: Programming Language :: Python :: 3.10
Classifier: Programming Language :: Python :: 3.11
Requires-Python: >=3.9
License-File: LICENSE
Requires-Dist: jsonschema (~=4.0)
Requires-Dist: aiohttp (~=3.0)
Requires-Dist: backoff (~=2.0)
Provides-Extra: deploy
Requires-Dist: twine ; extra == 'deploy'
Provides-Extra: dist
Requires-Dist: build ; extra == 'dist'
Provides-Extra: docs
Requires-Dist: sphinx ; extra == 'docs'
Requires-Dist: sphinx-rtd-theme ; extra == 'docs'
Requires-Dist: sphinx-automodapi ; extra == 'docs'
Requires-Dist: numpydoc ; extra == 'docs'
Provides-Extra: lint
Requires-Dist: flake8 ; extra == 'lint'
Provides-Extra: static
Requires-Dist: mypy ; extra == 'static'
Provides-Extra: test
Requires-Dist: pytest-asyncio ; extra == 'test'
Requires-Dist: pytest-cov ; extra == 'test'
